{
  "$schema": "https://developer.microsoft.com/json-schemas/fabric/item/report/definition/visualContainer/2.6.0/schema.json",
  "name": "4915715a145526d1e6ab",
  "position": {
    "x": 7.1641791044776122,
    "y": 8.0597014925373127,
    "z": 12000,
    "height": 50.149253731343279,
    "width": 343.88059701492534,
    "tabOrder": 12000
  },
  "visual": {
    "visualType": "textbox",
    "objects": {
      "general": [
        {
          "properties": {
            "paragraphs": [
              {
                "textRuns": [
                  {
                    "value": "Histórico de ventas: Industria de videojuegos",
                    "textStyle": {
                      "fontWeight": "bold",
                      "fontFamily": "Segoe UI",
                      "fontStyle": "italic",
                      "fontSize": "11pt",
                      "color": "#4c5d8a"
                    }
                  }
                ],
                "horizontalTextAlignment": "center"
              },
              {
                "textRuns": [
                  {
                    "value": "Reporte de ventas de la industria de videojuegos por categorías y años",
                    "textStyle": {
                      "fontFamily": "Segoe UI",
                      "fontStyle": "italic",
                      "fontSize": "8pt"
                    }
                  }
                ],
                "horizontalTextAlignment": "center"
              }
            ]
          }
        }
      ]
    },
    "drillFilterOtherVisuals": true
  }
}